{"2169ab8ad0b5262c17c18f39f03b87b66767d669dd01b0e2e9a352b74aa609a4":{"rank":"value-object","score":1.0,"nextThreshold":3,"totalEvents":1,"firstYear":2020,"lastYear":2020,"topics":{"ddd-core":1},"events":[{"date":"2020.07","title":"7月沙龍","type":"Meetup"}],"badges":["first","old-guard"]},"21efc183888c637e8797d4ff7d7e7316c1643f646c07e7ae436c202e6281365b":{"rank":"value-object","score":2.0,"nextThreshold":3,"totalEvents":1,"firstYear":2021,"lastYear":2021,"topics":{"ddd-core":1,"strategy":1},"events":[{"date":"2021.10","title":"第二屆年會 — 足跡 Footprints","type":"年會"}],"badges":["first","old-guard"]},"21b52de74edc7969fceab5de30ab7c4684d331b36b57998c807f0c5565841232":{"rank":"value-object","score":2.0,"nextThreshold":3,"totalEvents":1,"firstYear":2021,"lastYear":2021,"topics":{"ddd-core":1,"strategy":1},"events":[{"date":"2021.10","title":"第二屆年會 — 足跡 Footprints","type":"年會"}],"badges":["first","old-guard"]},"21b1d39ea9c249c9d59597c5c794293a427846bc688f93382914caf7805b36ff":{"rank":"value-object","score":1.0,"nextThreshold":3,"totalEvents":1,"firstYear":2019,"lastYear":2019,"topics":{"ddd-core":1,"architecture":1},"events":[{"date":"2019.05","title":"4th Meetup — LinkedIn 微服務開發遊歷","type":"Meetup"}],"badges":["first","old-guard"]},"213e89258910ebddc6f208caf892acc47a47d48275aa4e3cb99c55b418d805dc":{"rank":"value-object","score":2.0,"nextThreshold":3,"totalEvents":1,"firstYear":2020,"lastYear":2020,"topics":{"ddd-core":1,"strategy":1},"events":[{"date":"2020.11","title":"首屆年會 DDD Taiwan Conference 2020","type":"年會"}],"badges":["first","old-guard","founding"]},"2145502820d69ff7aa07698449fbaafe773319b1b0c61ffc5f9311f57c05c474":{"rank":"value-object","score":2.0,"nextThreshold":3,"totalEvents":1,"firstYear":2023,"lastYear":2023,"topics":{"ddd-core":1,"strategy":1},"events":[{"date":"2023.09","title":"第三屆年會 — 啟發","type":"年會"}],"badges":["first"]},"217ba6d58867986e73f5655bcd9e2c9fb30fae7050dd3bc712e5962f0884035f":{"rank":"value-object","score":1.5,"nextThreshold":3,"totalEvents":1,"firstYear":2024,"lastYear":2024,"topics":{"collaboration":1},"events":[{"date":"2024.07","title":"2024-07-06 全日工作坊","type":"工作坊"}],"badges":["first"]},"212065be946e7af64cb946d613df953e35816179a83c17f66dcae7948063edfa":{"rank":"value-object","score":2.0,"nextThreshold":3,"totalEvents":1,"firstYear":2024,"lastYear":2024,"topics":{"architecture":1,"strategy":1,"ddd-core":1},"events":[{"date":"2024.09","title":"第四屆年會 — System Design & Socio-technical","type":"年會"}],"badges":["first"]},"2107ce26b82e4205b15b2fcc3d1356b50939448e5af95ffcaa177825aafb4ae7":{"rank":"value-object","score":1.0,"nextThreshold":3,"totalEvents":1,"firstYear":2025,"lastYear":2025,"topics":{"ai":1,"collaboration":1},"events":[{"date":"2025.10","title":"DDDTW 台中 Tour — DaC × AIDLC × Vibe Coding","type":"Tour"}],"badges":["first","tourer"]},"21d46e03c3b43d0023fc3643193686b07f15cdfa09899c8c8105bd6f37ea2bac":{"rank":"value-object","score":1.0,"nextThreshold":3,"totalEvents":1,"firstYear":2026,"lastYear":2026,"topics":{"ddd-core":1},"events":[{"date":"2026.05","title":"2026-05-27 Meetup","type":"Meetup"}],"badges":["first"]}}