{"2d801a19a1583dfb62c97b6a4007baab02c058c0b759d6606e94c1327cac2af1":{"rank":"value-object","score":1.0,"nextThreshold":3,"totalEvents":1,"firstYear":2020,"lastYear":2020,"topics":{"ddd-core":1},"events":[{"date":"2020.03","title":"DDD 讀書會（2020 系列）","type":"讀書會"}],"badges":["first","old-guard"]},"2da54a5043c2f91409629c5719477d1d18c175c2e0d5e8e3dbc6d0e7664f0a5f":{"rank":"value-object","score":2.0,"nextThreshold":3,"totalEvents":1,"firstYear":2020,"lastYear":2020,"topics":{"ddd-core":1,"strategy":1},"events":[{"date":"2020.11","title":"首屆年會 DDD Taiwan Conference 2020","type":"年會"}],"badges":["first","old-guard","founding"]},"2d3d6e710efeeb17b11983011853b0d646e3b617fa1fc16942f3a4972b8776fe":{"rank":"value-object","score":2.5,"nextThreshold":3,"totalEvents":2,"firstYear":2024,"lastYear":2025,"topics":{"collaboration":2,"ai":1},"events":[{"date":"2025.10","title":"DDDTW 台中 Tour — DaC × AIDLC × Vibe Coding","type":"Tour"},{"date":"2024.06","title":"2024-06-22 工作坊","type":"工作坊"}],"badges":["first","tourer"]},"2db6569a63bf85be1cb3f2653aabaee2757a0122602d92a0d0f9e4635de04b9b":{"rank":"value-object","score":2.0,"nextThreshold":3,"totalEvents":1,"firstYear":2024,"lastYear":2024,"topics":{"architecture":1,"strategy":1,"ddd-core":1},"events":[{"date":"2024.09","title":"第四屆年會 — System Design & Socio-technical","type":"年會"}],"badges":["first"]},"2ddd01a5c0174e6784543f24a37928b6c56bf72b8afc2af493efa7253c094d34":{"rank":"value-object","score":1.0,"nextThreshold":3,"totalEvents":1,"firstYear":2025,"lastYear":2025,"topics":{"ai":1,"collaboration":1},"events":[{"date":"2025.10","title":"DDDTW 台中 Tour — DaC × AIDLC × Vibe Coding","type":"Tour"}],"badges":["first","tourer"]}}