{"351c1878fafa1f57fe495ae4adae766e7a417a96de1699b821be81db2da43aa0":{"rank":"entity","score":5.0,"nextThreshold":8,"totalEvents":4,"firstYear":2022,"lastYear":2024,"topics":{"collaboration":1,"eventstorming":1,"ddd-core":3,"architecture":1,"strategy":1},"events":[{"date":"2024.09","title":"第四屆年會 — System Design & Socio-technical","type":"年會"},{"date":"2024.02","title":"Event Storming 是個好東西","type":"Meetup"},{"date":"2023.01","title":"2023-01 線上直播","type":"Meetup"},{"date":"2022.06","title":"2022-06 Meetup","type":"Meetup"}],"badges":["first"]},"355d712bb1c7475d664446fc283b038f42eb46f3479902843faabab7b743fac7":{"rank":"entity","score":4.0,"nextThreshold":8,"totalEvents":2,"firstYear":2021,"lastYear":2023,"topics":{"ddd-core":2,"strategy":2},"events":[{"date":"2023.09","title":"第三屆年會 — 啟發","type":"年會"},{"date":"2021.10","title":"第二屆年會 — 足跡 Footprints","type":"年會"}],"badges":["first","old-guard"]},"35564b12eb07c43e74dc3b292d130a840457c40b8a0107c31d151171d6b45d8c":{"rank":"value-object","score":1.0,"nextThreshold":3,"totalEvents":1,"firstYear":2019,"lastYear":2019,"topics":{"ddd-core":1},"events":[{"date":"2019.07","title":"5th Meetup","type":"Meetup"}],"badges":["first","old-guard"]},"3510c1f4e64a4dbee68d84f67b2023ce816d2acfd70477170c9f87956c77a9f0":{"rank":"value-object","score":2.0,"nextThreshold":3,"totalEvents":2,"firstYear":2020,"lastYear":2025,"topics":{"ddd-core":1,"architecture":1,"ai":1},"events":[{"date":"2025.09","title":"DDD Tour 台南站 — Clean Architecture × n8n","type":"Tour"},{"date":"2020.09","title":"DDD Tour 台南站（2020）","type":"Tour"}],"badges":["first","old-guard","tourer"]},"35127334c5fbb1759d3c241d5a5f1d09dddbb0b1491eda5af083da37514d4153":{"rank":"entity","score":6.0,"nextThreshold":8,"totalEvents":4,"firstYear":2023,"lastYear":2025,"topics":{"ddd-core":3,"strategy":2,"architecture":2,"ai":1},"events":[{"date":"2025.04","title":"四月線上 Meetup — 閒聊架構與 MCP","type":"Meetup"},{"date":"2024.09","title":"第四屆年會 — System Design & Socio-technical","type":"年會"},{"date":"2023.09","title":"第三屆年會 — 啟發","type":"年會"},{"date":"2023.01","title":"2023-01 線上直播","type":"Meetup"}],"badges":["first"]}}