{"77e5b19846b9e261c6649a6c32bb997ecac41ac9cfebf5736a4c9880dc372312":{"rank":"value-object","score":1.0,"nextThreshold":3,"totalEvents":1,"firstYear":2019,"lastYear":2019,"topics":{"ddd-core":1},"events":[{"date":"2019.07","title":"5th Meetup","type":"Meetup"}],"badges":["first","old-guard"]},"771d9679da99df27010e1b741b4e4e71e4edeb208f8719d90de6bc97aa90ca9c":{"rank":"value-object","score":2.0,"nextThreshold":3,"totalEvents":1,"firstYear":2020,"lastYear":2020,"topics":{"ddd-core":1,"strategy":1},"events":[{"date":"2020.11","title":"首屆年會 DDD Taiwan Conference 2020","type":"年會"}],"badges":["first","old-guard","founding"]},"775f16f3c265443b733d61ad46a334d9efb99c117fc652a1a94bf8089d97264f":{"rank":"value-object","score":2.0,"nextThreshold":3,"totalEvents":1,"firstYear":2024,"lastYear":2024,"topics":{"architecture":1,"strategy":1,"ddd-core":1},"events":[{"date":"2024.09","title":"第四屆年會 — System Design & Socio-technical","type":"年會"}],"badges":["first"]},"77b680f13902e2228c8159280aa13b0b25cee2d72807bd2e14b02525dd3fa18d":{"rank":"value-object","score":1.5,"nextThreshold":3,"totalEvents":1,"firstYear":2025,"lastYear":2025,"topics":{"ai":1},"events":[{"date":"2025.05","title":"n8n 入門實作工作坊","type":"工作坊"}],"badges":["first"]}}