{"c381e3ef312c6770aaba7ce89954e5cc73b5524e390409443243d0e3cf41bb7e":{"rank":"value-object","score":1.0,"nextThreshold":3,"totalEvents":1,"firstYear":2021,"lastYear":2021,"topics":{"collaboration":1,"eventstorming":1},"events":[{"date":"2021.07","title":"Event Storming 的奧義之王者再臨","type":"Meetup"}],"badges":["first","old-guard"]},"c3eaefa245970996459888bd5c23c2d563e93c7dc1add71fa8c1680b33514fa7":{"rank":"value-object","score":2.0,"nextThreshold":3,"totalEvents":1,"firstYear":2021,"lastYear":2021,"topics":{"ddd-core":1,"strategy":1},"events":[{"date":"2021.10","title":"第二屆年會 — 足跡 Footprints","type":"年會"}],"badges":["first","old-guard"]},"c3708bdc367ac26e46e313fef67c0bb2c2b0129457890025ad741590f0502b2f":{"rank":"value-object","score":2.0,"nextThreshold":3,"totalEvents":1,"firstYear":2021,"lastYear":2021,"topics":{"ddd-core":1,"strategy":1},"events":[{"date":"2021.10","title":"第二屆年會 — 足跡 Footprints","type":"年會"}],"badges":["first","old-guard"]},"c3b4aa378b35064047fe7c61a0ebe8d805adc5467dc37645ec66271b02930975":{"rank":"value-object","score":2.0,"nextThreshold":3,"totalEvents":1,"firstYear":2020,"lastYear":2020,"topics":{"ddd-core":1,"strategy":1},"events":[{"date":"2020.11","title":"首屆年會 DDD Taiwan Conference 2020","type":"年會"}],"badges":["first","old-guard","founding"]},"c33e2fd8d8f126fc1dd9838fb39a3cc5589366ea7d4277249e1beeeddf9cfa15":{"rank":"value-object","score":2.0,"nextThreshold":3,"totalEvents":1,"firstYear":2020,"lastYear":2020,"topics":{"ddd-core":1,"strategy":1},"events":[{"date":"2020.11","title":"首屆年會 DDD Taiwan Conference 2020","type":"年會"}],"badges":["first","old-guard","founding"]},"c302fa5ba41dbeda33ae8280fd4f56217855ce871b75cec1e6428d5edb27cfb7":{"rank":"value-object","score":1.0,"nextThreshold":3,"totalEvents":1,"firstYear":2020,"lastYear":2020,"topics":{"ddd-core":1},"events":[{"date":"2020.09","title":"DDD Tour 台南站（2020）","type":"Tour"}],"badges":["first","old-guard","tourer"]},"c335be5995c5ec319119914c038de08df6c6eaf306b3aefb27160025926e3c90":{"rank":"value-object","score":1.0,"nextThreshold":3,"totalEvents":1,"firstYear":2023,"lastYear":2023,"topics":{"ddd-core":1},"events":[{"date":"2023.01","title":"2023-01 線上直播","type":"Meetup"}],"badges":["first"]},"c39b81d67ad9955a21b59c37458423ca31d522d388582b98e064deeb49f2d327":{"rank":"value-object","score":1.0,"nextThreshold":3,"totalEvents":1,"firstYear":2025,"lastYear":2025,"topics":{"ai":1,"collaboration":1},"events":[{"date":"2025.10","title":"DDDTW 台中 Tour — DaC × AIDLC × Vibe Coding","type":"Tour"}],"badges":["first","tourer"]}}